fastCloud/__init__.py
fastCloud/core/__init__.py
fastCloud/core/cloud_storage_factory.py
fastCloud/core/i_fast_cloud.py
fastCloud/core/api_providers/HTTPClientManager.py
fastCloud/core/api_providers/__init__.py
fastCloud/core/api_providers/i_upload_api.py
fastCloud/core/api_providers/replicate.py
fastCloud/core/api_providers/socaity.py
fastCloud/core/storage_providers/__init__.py
fastCloud/core/storage_providers/azure_storage.py
fastcloud-0.0.11.dist-info/METADATA
fastcloud-0.0.11.dist-info/WHEEL
fastcloud-0.0.11.dist-info/top_level.txt
fastcloud-0.0.11.dist-info/RECORD
