Metadata-Version: 2.4
Name: fastcloud
Version: 0.0.11
Summary: Upload and download files to common cloud providers like azure blob storage, s3 and more
Author: SocAIty
License: GPLv3
Project-URL: Repository, https://github.com/SocAIty/fastCloud
Project-URL: Homepage, https://www.socaity.ai
Requires-Python: >=3.8
Requires-Dist: media-toolkit>=0.2.17
Requires-Dist: httpx
Provides-Extra: azure
Requires-Dist: azure-storage-blob; extra == "azure"
Requires-Dist: httpx; extra == "azure"
